geoips_data_fusion/__init__.py
geoips_data_fusion/_version.py
geoips_data_fusion/commandline/__init__.py
geoips_data_fusion/commandline/args.py
geoips_data_fusion/commandline/data_fusion_procflow.py
geoips_data_fusion/plugins/__init__.py
geoips_data_fusion/plugins/modules/__init__.py
geoips_data_fusion/plugins/modules/algorithms/__init__.py
geoips_data_fusion/plugins/modules/algorithms/stitched.py
geoips_data_fusion/plugins/modules/output_formatters/__init__.py
geoips_data_fusion/plugins/modules/output_formatters/layered_imagery.py
geoips_data_fusion/plugins/modules/procflows/__init__.py
geoips_data_fusion/plugins/modules/procflows/data_fusion.py
geoips_data_fusion/plugins/yaml/product_defaults/Layered-Winds-Horizontal-Adjust.yaml
geoips_data_fusion/plugins/yaml/product_defaults/Layered-Winds-Horizontal-and-Vertical.yaml
geoips_data_fusion/plugins/yaml/product_defaults/Layered-Winds-Vertical-Adjust.yaml
geoips_data_fusion/plugins/yaml/product_defaults/Layered-Winds-Vertical-Default.yaml
geoips_data_fusion/plugins/yaml/products/abi.yaml
geoips_data_fusion/plugins/yaml/products/ahi.yaml
geoips_data_fusion/plugins/yaml/products/layered.yaml
geoips_data_fusion/plugins/yaml/products/seviri.yaml
geoips_data_fusion/plugins/yaml/products/stitched.yaml
geoips_data_fusion-1.16.1.post6.dev0.dist-info/LICENSE
geoips_data_fusion-1.16.1.post6.dev0.dist-info/METADATA
geoips_data_fusion-1.16.1.post6.dev0.dist-info/WHEEL
geoips_data_fusion-1.16.1.post6.dev0.dist-info/entry_points.txt
geoips_data_fusion-1.16.1.post6.dev0.dist-info/RECORD
