Metadata-Version: 2.3
Name: geoips_data_fusion
Version: 1.16.1.post6.dev0
Summary: Data Fusion GeoIPS Plugin Package
License: LICENSE
Requires-Python: >=3.10
Classifier: License :: Other/Proprietary License
Classifier: Programming Language :: Python :: 3
Classifier: Programming Language :: Python :: 3.10
Classifier: Programming Language :: Python :: 3.11
Classifier: Programming Language :: Python :: 3.12
Classifier: Programming Language :: Python :: 3.13
Project-URL: Repository, https://github.com/NRLMMD-GEOIPS/data_fusion
